simple_log_factory/__init__.py
simple_log_factory/log_factory.py
simple_log_factory-0.0.1.dist-info/METADATA
simple_log_factory-0.0.1.dist-info/WHEEL
simple_log_factory-0.0.1.dist-info/top_level.txt
simple_log_factory-0.0.1.dist-info/RECORD
