Metadata-Version: 2.1
Name: simple-log-factory
Version: 0.0.1
Summary: Simple Log Factory
Home-page: UNKNOWN
Author: Breno RdV
Author-email: hello@raccoon.ninja
License: UNKNOWN
Keywords: python,log,logging,factory
Platform: UNKNOWN
Classifier: Development Status :: 4 - Beta
Classifier: Intended Audience :: Developers
Classifier: License :: OSI Approved :: MIT License
Classifier: Programming Language :: Python :: 3
Classifier: Programming Language :: Python :: 3.6
Classifier: Programming Language :: Python :: 3.7
Classifier: Programming Language :: Python :: 3.8
Classifier: Programming Language :: Python :: 3.9
Classifier: Operating System :: MacOS :: MacOS X
Classifier: Operating System :: Microsoft :: Windows
Classifier: Operating System :: POSIX :: Linux
